aissemble_test_data_delivery_pyspark_model/generated/__init__.py
aissemble_test_data_delivery_pyspark_model/generated/dictionary/__init__.py
aissemble_test_data_delivery_pyspark_model/generated/dictionary/decimal_with_validation_base.py
aissemble_test_data_delivery_pyspark_model/generated/dictionary/float_with_validation_base.py
aissemble_test_data_delivery_pyspark_model/generated/dictionary/integer_with_validation_base.py
aissemble_test_data_delivery_pyspark_model/generated/dictionary/state_address_base.py
aissemble_test_data_delivery_pyspark_model/generated/dictionary/string_with_validation_base.py
aissemble_test_data_delivery_pyspark_model/generated/dictionary/type_with_policies_base.py
aissemble_test_data_delivery_pyspark_model/generated/dictionary/zipcode_base.py
aissemble_test_data_delivery_pyspark_model/generated/environment_base.py
aissemble_test_data_delivery_pyspark_model/generated/pipeline/pipeline_base.py
aissemble_test_data_delivery_pyspark_model/generated/record/__init__.py
aissemble_test_data_delivery_pyspark_model/generated/record/address_base.py
aissemble_test_data_delivery_pyspark_model/generated/record/address_field.py
aissemble_test_data_delivery_pyspark_model/generated/record/citizen_base.py
aissemble_test_data_delivery_pyspark_model/generated/record/citizen_field.py
aissemble_test_data_delivery_pyspark_model/generated/record/city_base.py
aissemble_test_data_delivery_pyspark_model/generated/record/city_field.py
aissemble_test_data_delivery_pyspark_model/generated/record/custom_data_base.py
aissemble_test_data_delivery_pyspark_model/generated/record/custom_data_field.py
aissemble_test_data_delivery_pyspark_model/generated/record/mayor_base.py
aissemble_test_data_delivery_pyspark_model/generated/record/mayor_field.py
aissemble_test_data_delivery_pyspark_model/generated/record/person_with_m_to_one_relation_base.py
aissemble_test_data_delivery_pyspark_model/generated/record/person_with_m_to_one_relation_field.py
aissemble_test_data_delivery_pyspark_model-2.0.0.dist-info/LICENSE
aissemble_test_data_delivery_pyspark_model-2.0.0.dist-info/METADATA
aissemble_test_data_delivery_pyspark_model-2.0.0.dist-info/WHEEL
aissemble_test_data_delivery_pyspark_model-2.0.0.dist-info/RECORD
